zeropos
