Metadata-Version: 1.1
Name: zeropos
Version: 0.1.2
Summary: Zero POS
